zakat/__init__.py
zakat/file_server.py
zakat/zakat_tracker.py
zakat-0.3.6.dist-info/licenses/LICENSE
zakat-0.3.6.dist-info/METADATA
zakat-0.3.6.dist-info/WHEEL
zakat-0.3.6.dist-info/top_level.txt
zakat-0.3.6.dist-info/RECORD
