Metadata-Version: 2.4
Name: zakat
Version: 0.3.6
Summary: A Python Library for Islamic Financial Management.
Author: Abdelaziz Elrashed Elshaikh Mohamed
Author-email: Abdelaziz Elrashed Elshaikh Mohamed <aeemh.sdn@gmail.com>
Project-URL: Homepage, https://github.com/vzool/zakat
Project-URL: Documentation, https://vzool.github.io/zakat/
Project-URL: Issues, https://github.com/vzool/zakat/issues
Classifier: Development Status :: 2 - Pre-Alpha
Classifier: Intended Audience :: Developers
Classifier: Programming Language :: Python :: 3
Classifier: Programming Language :: Python :: 3.10
Classifier: Programming Language :: Python :: 3.11
Classifier: Programming Language :: Python :: 3.12
Classifier: Programming Language :: Python :: 3.13
Classifier: License :: OSI Approved :: MIT License
Classifier: Operating System :: OS Independent
Requires-Python: >=3.10
License-File: LICENSE
Dynamic: author
Dynamic: license-file
Dynamic: requires-python
